pyClickModels.libs/libjson-c-ca0558d5.so.2.0.1
pyClickModels-0.0.2.dist-info/WHEEL
pyClickModels-0.0.2.dist-info/top_level.txt
pyClickModels-0.0.2.dist-info/LICENSE
pyClickModels-0.0.2.dist-info/METADATA
pyClickModels-0.0.2.dist-info/RECORD
pyClickModels/__version__.py
pyClickModels/DBN.pxd
pyClickModels/DBN.cpp
pyClickModels/DBN.cpython-38-x86_64-linux-gnu.so
pyClickModels/jsonc.pxd
pyClickModels/__init__.py
tests/test_cy_DBN.cpython-38-x86_64-linux-gnu.so
